gcf/__init__.py
gcf/gcf.py
gcf/gcf_data.csv
gcf/gcf_mining.py
gcf/gcf_scrape.py
gcf-0.0.3.dev3.dist-info/METADATA
gcf-0.0.3.dev3.dist-info/RECORD
gcf-0.0.3.dev3.dist-info/WHEEL
gcf-0.0.3.dev3.dist-info/entry_points.txt
gcf-0.0.3.dev3.dist-info/top_level.txt
