Metadata-Version: 2.1
Name: gcf
Version: 0.0.3.dev3
Summary: A Gadio infomation mining tool for fans of g-cores.com.
Home-page: https://github.com/bfdw/gcf
Author: riceknight
Author-email: riceknight@outlook.com
License: MIT
Download-URL: https://github.com/bfdw/gcf
Platform: UNKNOWN
Requires-Python: >=2.7
Requires-Dist: Click
Requires-Dist: bs4
Requires-Dist: requests
Requires-Dist: wcwidth
Requires-Dist: pandas
Requires-Dist: tabulate
